[
    {
      "id": 1,
      "nombre": "Bowl",
      "precio": 12.00,
      "imagen": "bowl.png"
    },
    {
      "id": 2,
      "nombre": "Comida para pájaros",
      "precio": 24.00,
      "imagen": "comida-pajaro.jpg"
    },
    {
      "id": 3,
      "nombre": "Cuerda para perros",
      "precio": 15.50,
      "imagen": "cuerda.png"
    },
    {
      "id": 4,
      "nombre": "Caseta",
      "precio": 69.99,
      "imagen": "caseta.png"
    },
    {
      "id": 5,
      "nombre": "Comida para perros Pure",
      "precio": 9.99,
      "imagen": "pure.png"
    },
    {
      "id": 6,
      "nombre": "Comida para gatos Royal Canin",
      "precio": 35.00,
      "imagen": "royal-canin.png"
    }
  ]
  